Metadata-Version: 1.1
Name: bfmplot
Version: 0.0.11
Summary: Snippet collections for plots how I make them.
Home-page: https://www.github.com/benmaier/bfmplot
Author: Benjamin F. Maier
Author-email: bfmaier@physik.hu-berlin.de
License: MIT
Platform: UNKNOWN
Classifier: Programming Language :: Python :: 3
